mycoffee/__init__.py
mycoffee/__main__.py
mycoffee/functions.py
mycoffee/params.py
mycoffee-2.1.dist-info/licenses/AUTHORS.md
mycoffee-2.1.dist-info/licenses/LICENSE
mycoffee-2.1.dist-info/METADATA
mycoffee-2.1.dist-info/WHEEL
mycoffee-2.1.dist-info/entry_points.txt
mycoffee-2.1.dist-info/top_level.txt
mycoffee-2.1.dist-info/RECORD
